vignereED.py
vignereED-0.0.1.dist-info/METADATA
vignereED-0.0.1.dist-info/WHEEL
vignereED-0.0.1.dist-info/top_level.txt
vignereED-0.0.1.dist-info/RECORD
