Metadata-Version: 2.1
Name: vignereED
Version: 0.0.1
Summary: A Demo app for encryption and decryption of messages using vignere cipher
Home-page: UNKNOWN
Author: R.Raja Subramanian
Author-email: rajasubramanian.r1@gmail.com
License: UNKNOWN
Platform: UNKNOWN
